vntickers/.DS_Store
vntickers/.claude/settings.local.json
vntickers/__init__.py
vntickers/loader.py
vntickers/validators/__init__.py
vntickers/validators/base.py
vntickers/validators/vietfin.py
vntickers/validators/vnquant.py
vntickers/validators/vnstock.py
vntickers/vietfin_loader.py
vntickers/vnquant_loader.py
vntickers/vnstock_loader.py
vntickers-0.2.0.dist-info/WHEEL
vntickers-0.2.0.dist-info/entry_points.txt
vntickers-0.2.0.dist-info/METADATA
vntickers-0.2.0.dist-info/RECORD
