Metadata-Version: 2.3
Name: vntickers
Version: 0.2.0
Summary: A Python package for fetching Vietnamese stock market data from multiple sources
Author: gahoccode
Author-email: gahoccode <dautuchungkhoan1200@gmail.com>
Classifier: Development Status :: 3 - Alpha
Classifier: Intended Audience :: Developers
Classifier: Intended Audience :: Financial and Insurance Industry
Classifier: License :: OSI Approved :: MIT License
Classifier: Programming Language :: Python :: 3
Classifier: Programming Language :: Python :: 3.10
Classifier: Programming Language :: Python :: 3.11
Classifier: Programming Language :: Python :: 3.12
Classifier: Topic :: Office/Business :: Financial :: Investment
Requires-Dist: vnstock>=3.2.6
Requires-Dist: vnquant
Requires-Dist: vietfin
Requires-Dist: pandas
Requires-Dist: pydantic>=2.0.0
Requires-Python: >=3.10
Project-URL: Homepage, https://github.com/gahoccode/vntickers
Project-URL: Issues, https://github.com/gahoccode/vntickers/issues
Project-URL: Repository, https://github.com/gahoccode/vntickers
